{
  "Charts.jsx": [
    {
      "question": "What is the purpose of the `useEffect` hook in this code snippet?",
      "scores": {
        "Relevance": 5,
        "Specificity": 4,
        "Depth": 3,
        "clarity": 5
      }
    },
    {
      "question": "How does the `fetchTables` function from the `Charts` component fetch data from an API?",
      "scores": {
        "Relevance": 5,
        "Specificity": 4,
        "Depth": 3,
        "clarity": 5
      }
    },
    {
      "question": "Can you explain the logic behind the `getNeededCols` function, especially with regards to the different types of charts (bar chart, line chart)?",
      "scores": {
        "Relevance": 5,
        "Specificity": 4,
        "Depth": 4,
        "clarity": 4
      }
    },
    {
      "question": "What are some potential issues or edge cases that this code might encounter when loading data from the API?",
      "scores": {
        "Relevance": 5,
        "Specificity": 3,
        "Depth": 5,
        "clarity": 4
      }
    },
    {
      "question": "How does the code handle errors, such as network failures or invalid responses from the API?",
      "scores": {
        "Relevance": 5,
        "Specificity": 4,
        "Depth": 4,
        "clarity": 5
      }
    },
    {
      "question": "Are there any specific optimizations or improvements that could be made to the code to improve performance or scalability?",
      "scores": {
        "Relevance": 4,
        "Specificity": 2,
        "Depth": 5,
        "clarity": 4
      }
    },
    {
      "question": "Can you explain how the `charts-grid` and `chart-card` components are used in this context?",
      "scores": {
        "Relevance": 4,
        "Specificity": 3,
        "Depth": 2,
        "clarity": 5
      }
    }
  ]
}